pySW/__init__.py
pySW/commSW.py
pySW-1.4.dist-info/LICENSE.txt
pySW-1.4.dist-info/METADATA
pySW-1.4.dist-info/WHEEL
pySW-1.4.dist-info/top_level.txt
pySW-1.4.dist-info/RECORD
