Metadata-Version: 2.1
Name: pySW
Version: 1.4
Summary: A Wrapper around Solidworks VBA API for Automating Geometry Modifications for Python based Optimization and Design Space Exploration.
Home-page: https://github.com/kalyanpi4/pySW
Author: Kalyan Inamdar
Author-email: kalyaninamdar@protonmail.com
License: UNKNOWN
Download-URL: https://github.com/kalyanpi4/pySW/archive/V1.4.tar.gz
Platform: UNKNOWN
Classifier: Programming Language :: Python :: 3
Requires-Python: >=3.6
Requires-Dist: numpy
Requires-Dist: pandas
Requires-Dist: pywin32
